{
  "generationParameters": {
    "generationDate": "Wed Jul 22 2026 04:18:34 GMT+0000 (Coordinated Universal Time)",
    "generatorPlatform": "SAP Business Application Studio",
    "serviceType": "Local CAP",
    "metadataFilename": "",
    "serviceUrl": "http://localhost:4004/odata/v4/alert/",
    "appName": "emailmanagement",
    "appTitle": "Email Alert Management",
    "appDescription": "An SAP Fiori application.",
    "appNamespace": "hpbuysell.adm.emlmnmt",
    "ui5Theme": "sap_horizon",
    "ui5Version": "1.150.0",
    "enableEslint": true,
    "enableTypeScript": false,
    "showMockDataInfo": false,
    "generatorVersion": "1.29.0",
    "template": "Basic V4",
    "generatorName": "SAP Fiori Application Generator",
    "entityRelatedConfig": [],
    "launchText": "To launch the generated app, start your CAP project:  and navigate to the following location in your browser:\n\nhttp://localhost:4004/hpbuysell.adm.emlmnmt.emailmanagement/index.html"
  }
}
